pcapforge_core/__init__.py
pcapforge_core-0.0.1.dist-info/METADATA
pcapforge_core-0.0.1.dist-info/WHEEL
pcapforge_core-0.0.1.dist-info/top_level.txt
pcapforge_core-0.0.1.dist-info/RECORD
