Metadata-Version: 2.4
Name: pcapforge-core
Version: 0.0.1
Summary: Fast packet capture processor and feature extractor - Core library
Home-page: https://github.com/pcapforge/pcapforge
Author: Colin Knizek
Author-email: Colin Knizek <pcapforge@users.noreply.github.com>
License: Apache-2.0
Project-URL: Homepage, https://github.com/pcapforge/pcapforge
Project-URL: Repository, https://github.com/pcapforge/pcapforge
Project-URL: Issues, https://github.com/pcapforge/pcapforge/issues
Keywords: pcap,packet,network,analysis,capture,pcapng
Classifier: Development Status :: 1 - Planning
Classifier: Intended Audience :: Developers
Classifier: Topic :: System :: Networking
Classifier: License :: OSI Approved :: Apache Software License
Classifier: Programming Language :: Python :: 3
Requires-Python: >=3.8
Dynamic: author
Dynamic: home-page
Dynamic: requires-python
